snmpsim/__init__.py
snmpsim/commands/__init__.py
snmpsim/commands/cmd2rec.py
snmpsim/commands/mib2rec.py
snmpsim/commands/pcap2rec.py
snmpsim/commands/rec2rec.py
snmpsim/commands/responder.py
snmpsim/commands/responder_lite.py
snmpsim/confdir.py
snmpsim/controller.py
snmpsim/daemon.py
snmpsim/data/1.3.6.1.6.1.1.0/127.0.0.1.snmprec
snmpsim/data/1.3.6.1.6.1.1.0/README-v2c.txt
snmpsim/data/1.3.6.1.6.1.1.0/README-v3.txt
snmpsim/data/README.txt
snmpsim/data/foreignformats/README.txt
snmpsim/data/foreignformats/linux.snmpwalk
snmpsim/data/foreignformats/winxp1.snmpwalk
snmpsim/data/foreignformats/winxp2.sapwalk
snmpsim/data/mib2dev/host-resources-mib.snmprec
snmpsim/data/mib2dev/ip-mib.snmprec
snmpsim/data/mib2dev/tcp-mib.snmprec
snmpsim/data/mib2dev/udp-mib.snmprec
snmpsim/data/public/1.3.6.1.2.1.100.1.13.0.snmprec
snmpsim/data/public/1.3.6.1.2.1.100.1.2.0/README-v2c.txt
snmpsim/data/public/1.3.6.1.2.1.100.1.2.0/README-v3.txt
snmpsim/data/public/1.3.6.1.2.1.100.1.2.0/__1.snmprec
snmpsim/data/public/1.3.6.1.6.1.1.0/127.0.0.1.snmprec
snmpsim/data/public/1.3.6.1.6.1.1.0/README-v2c.txt
snmpsim/data/public/1.3.6.1.6.1.1.0/README-v3.txt
snmpsim/data/public/README-v2c.txt
snmpsim/data/public/README-v3.txt
snmpsim/data/public.snmprec
snmpsim/data/recorded/eaton-9PX-partial-walk.snmprec
snmpsim/data/recorded/linksys-system.snmprec
snmpsim/data/recorded/linux-full-walk.snmprec
snmpsim/data/recorded/solaris-system.snmprec
snmpsim/data/recorded/udp-endpoint-table-walk.snmprec
snmpsim/data/recorded/winxp-full-walk.snmprec
snmpsim/data/variation/README.txt
snmpsim/data/variation/delay.snmprec
snmpsim/data/variation/error.snmprec
snmpsim/data/variation/multiplex/00000.snmprec
snmpsim/data/variation/multiplex/00001.snmprec
snmpsim/data/variation/multiplex/00002.snmprec
snmpsim/data/variation/multiplex/00003.snmprec
snmpsim/data/variation/multiplex/00004.snmprec
snmpsim/data/variation/multiplex/00005.snmprec
snmpsim/data/variation/multiplex/00006.snmprec
snmpsim_lextudio-1.1.1.dist-info/LICENSE.txt
snmpsim_lextudio-1.1.1.dist-info/METADATA
snmpsim_lextudio-1.1.1.dist-info/WHEEL
snmpsim_lextudio-1.1.1.dist-info/entry_points.txt
snmpsim_lextudio-1.1.1.dist-info/RECORD
