Metadata-Version: 2.1
Name: snmpsim-lextudio
Version: 1.1.1
Summary: SNMP Simulator is a tool that acts as multitude of SNMP Agents built into real physical devices, from SNMP Manager's point of view. Simulator builds and uses a database of physical devices' SNMP footprints to respond like their original counterparts do.
Home-page: https://github.com/lextudio/snmpsim
License: BSD-2-Clause
Author: Ilya Etingof
Author-email: etingof@gmail.com
Requires-Python: >=3.8,<4.0
Classifier: Development Status :: 5 - Production/Stable
Classifier: Environment :: Console
Classifier: Intended Audience :: Developers
Classifier: Intended Audience :: Education
Classifier: Intended Audience :: Information Technology
Classifier: Intended Audience :: System Administrators
Classifier: Intended Audience :: Telecommunications Industry
Classifier: License :: OSI Approved :: BSD License
Classifier: Natural Language :: English
Classifier: Operating System :: OS Independent
Classifier: Programming Language :: Python :: 3
Classifier: Programming Language :: Python :: 3.8
Classifier: Programming Language :: Python :: 3.9
Classifier: Programming Language :: Python :: 3.10
Classifier: Programming Language :: Python :: 3.11
Classifier: Programming Language :: Python :: 3.12
Classifier: Topic :: Communications
Classifier: Topic :: System :: Monitoring
Classifier: Topic :: System :: Networking :: Monitoring
Requires-Dist: pysnmp-lextudio (>=6.1.0,<7.0.0)
Project-URL: Repository, https://github.com/lextudio/snmpsim
